odoo/addons/sale_margin_delivered_dropshipping/README.rst
odoo/addons/sale_margin_delivered_dropshipping/__init__.py
odoo/addons/sale_margin_delivered_dropshipping/__manifest__.py
odoo/addons/sale_margin_delivered_dropshipping/i18n/it.po
odoo/addons/sale_margin_delivered_dropshipping/i18n/sale_margin_delivered_dropshipping.pot
odoo/addons/sale_margin_delivered_dropshipping/models/__init__.py
odoo/addons/sale_margin_delivered_dropshipping/models/sale_margin.py
odoo/addons/sale_margin_delivered_dropshipping/readme/CONFIGURE.rst
odoo/addons/sale_margin_delivered_dropshipping/readme/CONTRIBUTORS.rst
odoo/addons/sale_margin_delivered_dropshipping/readme/DESCRIPTION.rst
odoo/addons/sale_margin_delivered_dropshipping/readme/USAGE.rst
odoo/addons/sale_margin_delivered_dropshipping/static/description/icon.png
odoo/addons/sale_margin_delivered_dropshipping/static/description/index.html
odoo/addons/sale_margin_delivered_dropshipping/tests/__init__.py
odoo/addons/sale_margin_delivered_dropshipping/tests/test_sale_margin_delivered_dropship.py
odoo_addon_sale_margin_delivered_dropshipping-16.0.1.0.1.3.dist-info/METADATA
odoo_addon_sale_margin_delivered_dropshipping-16.0.1.0.1.3.dist-info/WHEEL
odoo_addon_sale_margin_delivered_dropshipping-16.0.1.0.1.3.dist-info/top_level.txt
odoo_addon_sale_margin_delivered_dropshipping-16.0.1.0.1.3.dist-info/RECORD
